baserowsdk/client.py
baserowsdk/const.py
baserowsdk/models/base.py
baserowsdk/models/field.py
baserowsdk/models/row.py
baserowsdk/models/table.py
baserowsdk/sdk_exception.py
baserowsdk-0.1.2.dist-info/LICENSE
baserowsdk-0.1.2.dist-info/METADATA
baserowsdk-0.1.2.dist-info/WHEEL
baserowsdk-0.1.2.dist-info/RECORD
