Metadata-Version: 2.1
Name: baserowsdk
Version: 0.1.2
Summary: Baserow OpenAPI Python SDK
Author: shenyubao.
Author-email: ssybb1988@gmail.com
Requires-Python: >=3.8,<4.0
Classifier: Programming Language :: Python :: 3
Classifier: Programming Language :: Python :: 3.8
Classifier: Programming Language :: Python :: 3.9
Classifier: Programming Language :: Python :: 3.10
Classifier: Programming Language :: Python :: 3.11
Classifier: Programming Language :: Python :: 3.12
Classifier: Programming Language :: Python :: 3.13
Requires-Dist: certifi (>=2023.7.22,<2024.0.0)
Requires-Dist: charset-normalizer (>=3.2.0,<4.0.0)
Requires-Dist: environs (>=9.5.0,<10.0.0)
Requires-Dist: idna (>=3.4,<4.0)
Requires-Dist: marshmallow (>=3.20.1,<4.0.0)
Requires-Dist: requests (>=2.31.0,<3.0.0)
Requires-Dist: urllib3 (>=2.0.4,<3.0.0)
